VisionKit/__init__.py
VisionKit/kits.py
VisionKit/main.py
VisionKit/kitfiles/__init__.py
VisionKit/kitfiles/greentape.py
VisionKit/kitfiles/raidershirtfind.py
VisionKit-0.2rc6.dist-info/METADATA
VisionKit-0.2rc6.dist-info/RECORD
VisionKit-0.2rc6.dist-info/WHEEL
VisionKit-0.2rc6.dist-info/top_level.txt
