Metadata-Version: 2.1
Name: VisionKit
Version: 0.2rc6
Summary: Making computer vision easy with wrappers and presets
Home-page: https://github.com/frc5024/VisionKit
Author: Evan Pratten
Author-email: ewpratten@gmail.com
License: MIT
Platform: UNKNOWN
Classifier: Programming Language :: Python :: 3
Classifier: License :: OSI Approved :: MIT License
Classifier: Operating System :: OS Independent
Classifier: Development Status :: 5 - Production/Stable
Requires-Dist: opencv-python
Requires-Dist: pynetworktables
